<annotation>
	<folder>Basil</folder>
	<filename>IMG_20201030_Basil_healthy_0_7594.jpg</filename>
	<path>C:\Users\eduar\Escritorio\lalo\Basil\IMG_20201030_Basil_healthy_0_7594.jpg</path>
	<source>
		<database>Unknown</database>
	</source>
	<size>
		<width>2490</width>
		<height>3059</height>
		<depth>3</depth>
	</size>
	<segmented>0</segmented>
	<object>
		<name>Basil_healthy</name>
		<pose>Unspecified</pose>
		<truncated>0</truncated>
		<difficult>0</difficult>
		<bndbox>
			<xmin>701</xmin>
			<ymin>907</ymin>
			<xmax>1882</xmax>
			<ymax>2516</ymax>
		</bndbox>
	</object>
	<object>
		<name>Basil_healthy</name>
		<pose>Unspecified</pose>
		<truncated>0</truncated>
		<difficult>0</difficult>
		<bndbox>
			<xmin>344</xmin>
			<ymin>298</ymin>
			<xmax>1197</xmax>
			<ymax>922</ymax>
		</bndbox>
	</object>
	<object>
		<name>Basil_healthy</name>
		<pose>Unspecified</pose>
		<truncated>1</truncated>
		<difficult>0</difficult>
		<bndbox>
			<xmin>1153</xmin>
			<ymin>2273</ymin>
			<xmax>2420</xmax>
			<ymax>3059</ymax>
		</bndbox>
	</object>
</annotation>
