<annotation>
	<folder>Basil</folder>
	<filename>IMG_20201113_Basil_healthy_0_1619.jpg</filename>
	<path>C:\Users\eduar\Escritorio\lalo\Basil\IMG_20201113_Basil_healthy_0_1619.jpg</path>
	<source>
		<database>Unknown</database>
	</source>
	<size>
		<width>2596</width>
		<height>3033</height>
		<depth>3</depth>
	</size>
	<segmented>0</segmented>
	<object>
		<name>Basil_healthy</name>
		<pose>Unspecified</pose>
		<truncated>0</truncated>
		<difficult>0</difficult>
		<bndbox>
			<xmin>944</xmin>
			<ymin>271</ymin>
			<xmax>2430</xmax>
			<ymax>2933</ymax>
		</bndbox>
	</object>
</annotation>
