<annotation>
	<folder>Basil</folder>
	<filename>IMG_20200826_basil_healthy_0_3671.jpg</filename>
	<path>C:\Users\eduar\Escritorio\lalo\Basil\IMG_20200826_basil_healthy_0_3671.jpg</path>
	<source>
		<database>Unknown</database>
	</source>
	<size>
		<width>3701</width>
		<height>2193</height>
		<depth>3</depth>
	</size>
	<segmented>0</segmented>
	<object>
		<name>Basil_healthy</name>
		<pose>Unspecified</pose>
		<truncated>0</truncated>
		<difficult>0</difficult>
		<bndbox>
			<xmin>1642</xmin>
			<ymin>121</ymin>
			<xmax>3065</xmax>
			<ymax>1631</ymax>
		</bndbox>
	</object>
</annotation>
