<annotation>
	<folder>Basil</folder>
	<filename>IMG_20201113_Basil_healthy_0_106.jpg</filename>
	<path>C:\Users\eduar\Escritorio\lalo\Basil\IMG_20201113_Basil_healthy_0_106.jpg</path>
	<source>
		<database>Unknown</database>
	</source>
	<size>
		<width>3311</width>
		<height>2628</height>
		<depth>3</depth>
	</size>
	<segmented>0</segmented>
	<object>
		<name>Basil_healthy</name>
		<pose>Unspecified</pose>
		<truncated>0</truncated>
		<difficult>0</difficult>
		<bndbox>
			<xmin>692</xmin>
			<ymin>303</ymin>
			<xmax>2571</xmax>
			<ymax>2552</ymax>
		</bndbox>
	</object>
	<object>
		<name>Basil_healthy</name>
		<pose>Unspecified</pose>
		<truncated>1</truncated>
		<difficult>0</difficult>
		<bndbox>
			<xmin>1959</xmin>
			<ymin>1</ymin>
			<xmax>3113</xmax>
			<ymax>1089</ymax>
		</bndbox>
	</object>
	<object>
		<name>Basil_healthy</name>
		<pose>Unspecified</pose>
		<truncated>0</truncated>
		<difficult>0</difficult>
		<bndbox>
			<xmin>609</xmin>
			<ymin>123</ymin>
			<xmax>1771</xmax>
			<ymax>719</ymax>
		</bndbox>
	</object>
</annotation>
