<annotation>
	<folder>Basil</folder>
	<filename>IMG_20201113_Basil_healthy_0_4696.jpg</filename>
	<path>C:\Users\eduar\Escritorio\lalo\Basil\IMG_20201113_Basil_healthy_0_4696.jpg</path>
	<source>
		<database>Unknown</database>
	</source>
	<size>
		<width>2763</width>
		<height>3480</height>
		<depth>3</depth>
	</size>
	<segmented>0</segmented>
	<object>
		<name>Basil_healthy</name>
		<pose>Unspecified</pose>
		<truncated>0</truncated>
		<difficult>0</difficult>
		<bndbox>
			<xmin>1525</xmin>
			<ymin>125</ymin>
			<xmax>2103</xmax>
			<ymax>1414</ymax>
		</bndbox>
	</object>
	<object>
		<name>Basil_healthy</name>
		<pose>Unspecified</pose>
		<truncated>1</truncated>
		<difficult>0</difficult>
		<bndbox>
			<xmin>808</xmin>
			<ymin>598</ymin>
			<xmax>2357</xmax>
			<ymax>3480</ymax>
		</bndbox>
	</object>
</annotation>
