<annotation>
	<folder>Basil</folder>
	<filename>IMG_20200819_192208.jpg</filename>
	<path>C:\Users\eduar\Escritorio\lalo\Basil\IMG_20200819_192208.jpg</path>
	<source>
		<database>Unknown</database>
	</source>
	<size>
		<width>2976</width>
		<height>3968</height>
		<depth>3</depth>
	</size>
	<segmented>0</segmented>
	<object>
		<name>Basil_healthy</name>
		<pose>Unspecified</pose>
		<truncated>0</truncated>
		<difficult>0</difficult>
		<bndbox>
			<xmin>1157</xmin>
			<ymin>2032</ymin>
			<xmax>1719</xmax>
			<ymax>2582</ymax>
		</bndbox>
	</object>
	<object>
		<name>Basil_cercospora_leaf_spot</name>
		<pose>Unspecified</pose>
		<truncated>0</truncated>
		<difficult>0</difficult>
		<bndbox>
			<xmin>1392</xmin>
			<ymin>1753</ymin>
			<xmax>2074</xmax>
			<ymax>2190</ymax>
		</bndbox>
	</object>
	<object>
		<name>Basil_healthy</name>
		<pose>Unspecified</pose>
		<truncated>0</truncated>
		<difficult>0</difficult>
		<bndbox>
			<xmin>1276</xmin>
			<ymin>1128</ymin>
			<xmax>1869</xmax>
			<ymax>1790</ymax>
		</bndbox>
	</object>
	<object>
		<name>Basil_healthy</name>
		<pose>Unspecified</pose>
		<truncated>0</truncated>
		<difficult>0</difficult>
		<bndbox>
			<xmin>1917</xmin>
			<ymin>919</ymin>
			<xmax>2186</xmax>
			<ymax>1582</ymax>
		</bndbox>
	</object>
	<object>
		<name>Basil_healthy</name>
		<pose>Unspecified</pose>
		<truncated>0</truncated>
		<difficult>0</difficult>
		<bndbox>
			<xmin>2044</xmin>
			<ymin>1157</ymin>
			<xmax>2476</xmax>
			<ymax>1696</ymax>
		</bndbox>
	</object>
	<object>
		<name>Basil_healthy</name>
		<pose>Unspecified</pose>
		<truncated>0</truncated>
		<difficult>0</difficult>
		<bndbox>
			<xmin>1988</xmin>
			<ymin>1640</ymin>
			<xmax>2532</xmax>
			<ymax>1969</ymax>
		</bndbox>
	</object>
	<object>
		<name>Basil_healthy</name>
		<pose>Unspecified</pose>
		<truncated>0</truncated>
		<difficult>0</difficult>
		<bndbox>
			<xmin>2207</xmin>
			<ymin>1628</ymin>
			<xmax>2813</xmax>
			<ymax>1784</ymax>
		</bndbox>
	</object>
</annotation>
