<annotation>
	<folder>Basil</folder>
	<filename>IMG_20200826_basil_healthy_0_4837.jpg</filename>
	<path>C:\Users\eduar\Escritorio\lalo\Basil\IMG_20200826_basil_healthy_0_4837.jpg</path>
	<source>
		<database>Unknown</database>
	</source>
	<size>
		<width>3952</width>
		<height>2788</height>
		<depth>3</depth>
	</size>
	<segmented>0</segmented>
	<object>
		<name>Basil_healthy</name>
		<pose>Unspecified</pose>
		<truncated>0</truncated>
		<difficult>0</difficult>
		<bndbox>
			<xmin>1384</xmin>
			<ymin>869</ymin>
			<xmax>2762</xmax>
			<ymax>2377</ymax>
		</bndbox>
	</object>
	<object>
		<name>Basil_healthy</name>
		<pose>Unspecified</pose>
		<truncated>0</truncated>
		<difficult>0</difficult>
		<bndbox>
			<xmin>2058</xmin>
			<ymin>795</ymin>
			<xmax>3518</xmax>
			<ymax>1868</ymax>
		</bndbox>
	</object>
</annotation>
