<annotation>
	<folder>Basil</folder>
	<filename>IMG_20201113_Basil_healthy_0_1605.jpg</filename>
	<path>C:\Users\eduar\Escritorio\lalo\Basil\IMG_20201113_Basil_healthy_0_1605.jpg</path>
	<source>
		<database>Unknown</database>
	</source>
	<size>
		<width>2255</width>
		<height>3267</height>
		<depth>3</depth>
	</size>
	<segmented>0</segmented>
	<object>
		<name>Basil_healthy</name>
		<pose>Unspecified</pose>
		<truncated>0</truncated>
		<difficult>0</difficult>
		<bndbox>
			<xmin>743</xmin>
			<ymin>776</ymin>
			<xmax>1866</xmax>
			<ymax>1975</ymax>
		</bndbox>
	</object>
	<object>
		<name>Basil_healthy</name>
		<pose>Unspecified</pose>
		<truncated>0</truncated>
		<difficult>0</difficult>
		<bndbox>
			<xmin>511</xmin>
			<ymin>1533</ymin>
			<xmax>1401</xmax>
			<ymax>2330</ymax>
		</bndbox>
	</object>
	<object>
		<name>Basil_healthy</name>
		<pose>Unspecified</pose>
		<truncated>1</truncated>
		<difficult>0</difficult>
		<bndbox>
			<xmin>648</xmin>
			<ymin>2222</ymin>
			<xmax>1908</xmax>
			<ymax>3267</ymax>
		</bndbox>
	</object>
</annotation>
