<annotation>
	<folder>Basil</folder>
	<filename>IMG_20201113_Basil_healthy_0_4686.jpg</filename>
	<path>C:\Users\eduar\Escritorio\lalo\Basil\IMG_20201113_Basil_healthy_0_4686.jpg</path>
	<source>
		<database>Unknown</database>
	</source>
	<size>
		<width>3708</width>
		<height>1951</height>
		<depth>3</depth>
	</size>
	<segmented>0</segmented>
	<object>
		<name>Basil_healthy</name>
		<pose>Unspecified</pose>
		<truncated>0</truncated>
		<difficult>0</difficult>
		<bndbox>
			<xmin>1176</xmin>
			<ymin>591</ymin>
			<xmax>3238</xmax>
			<ymax>1585</ymax>
		</bndbox>
	</object>
	<object>
		<name>Basil_healthy</name>
		<pose>Unspecified</pose>
		<truncated>1</truncated>
		<difficult>0</difficult>
		<bndbox>
			<xmin>1</xmin>
			<ymin>1050</ymin>
			<xmax>968</xmax>
			<ymax>1750</ymax>
		</bndbox>
	</object>
</annotation>
