<annotation>
	<folder>Basil</folder>
	<filename>IMG_20200826_basil_healthy_0_6974.jpg</filename>
	<path>C:\Users\eduar\Escritorio\lalo\Basil\IMG_20200826_basil_healthy_0_6974.jpg</path>
	<source>
		<database>Unknown</database>
	</source>
	<size>
		<width>2469</width>
		<height>2684</height>
		<depth>3</depth>
	</size>
	<segmented>0</segmented>
	<object>
		<name>Basil_healthy</name>
		<pose>Unspecified</pose>
		<truncated>0</truncated>
		<difficult>0</difficult>
		<bndbox>
			<xmin>383</xmin>
			<ymin>773</ymin>
			<xmax>2466</xmax>
			<ymax>2523</ymax>
		</bndbox>
	</object>
	<object>
		<name>Basil_healthy</name>
		<pose>Unspecified</pose>
		<truncated>0</truncated>
		<difficult>0</difficult>
		<bndbox>
			<xmin>771</xmin>
			<ymin>234</ymin>
			<xmax>2154</xmax>
			<ymax>1138</ymax>
		</bndbox>
	</object>
</annotation>
