<annotation>
	<folder>Basil</folder>
	<filename>IMG_20201113_Basil_healthy_0_8505.jpg</filename>
	<path>C:\Users\eduar\Escritorio\lalo\Basil\IMG_20201113_Basil_healthy_0_8505.jpg</path>
	<source>
		<database>Unknown</database>
	</source>
	<size>
		<width>3856</width>
		<height>2679</height>
		<depth>3</depth>
	</size>
	<segmented>0</segmented>
	<object>
		<name>Basil_healthy</name>
		<pose>Unspecified</pose>
		<truncated>0</truncated>
		<difficult>0</difficult>
		<bndbox>
			<xmin>2027</xmin>
			<ymin>708</ymin>
			<xmax>3411</xmax>
			<ymax>2421</ymax>
		</bndbox>
	</object>
	<object>
		<name>Basil_healthy</name>
		<pose>Unspecified</pose>
		<truncated>0</truncated>
		<difficult>0</difficult>
		<bndbox>
			<xmin>1301</xmin>
			<ymin>999</ymin>
			<xmax>2073</xmax>
			<ymax>1790</ymax>
		</bndbox>
	</object>
	<object>
		<name>Basil_healthy</name>
		<pose>Unspecified</pose>
		<truncated>1</truncated>
		<difficult>0</difficult>
		<bndbox>
			<xmin>540</xmin>
			<ymin>1383</ymin>
			<xmax>1319</xmax>
			<ymax>2679</ymax>
		</bndbox>
	</object>
	<object>
		<name>Basil_healthy</name>
		<pose>Unspecified</pose>
		<truncated>0</truncated>
		<difficult>0</difficult>
		<bndbox>
			<xmin>406</xmin>
			<ymin>166</ymin>
			<xmax>1572</xmax>
			<ymax>1570</ymax>
		</bndbox>
	</object>
</annotation>
