<annotation>
	<folder>Basil</folder>
	<filename>IMG_20201113_Basil_healthy_0_1664.jpg</filename>
	<path>C:\Users\eduar\Escritorio\lalo\Basil\IMG_20201113_Basil_healthy_0_1664.jpg</path>
	<source>
		<database>Unknown</database>
	</source>
	<size>
		<width>3421</width>
		<height>2294</height>
		<depth>3</depth>
	</size>
	<segmented>0</segmented>
	<object>
		<name>Basil_healthy</name>
		<pose>Unspecified</pose>
		<truncated>1</truncated>
		<difficult>0</difficult>
		<bndbox>
			<xmin>1</xmin>
			<ymin>63</ymin>
			<xmax>1973</xmax>
			<ymax>1954</ymax>
		</bndbox>
	</object>
	<object>
		<name>Basil_healthy</name>
		<pose>Unspecified</pose>
		<truncated>1</truncated>
		<difficult>0</difficult>
		<bndbox>
			<xmin>1748</xmin>
			<ymin>1</ymin>
			<xmax>2519</xmax>
			<ymax>644</ymax>
		</bndbox>
	</object>
	<object>
		<name>Basil_healthy</name>
		<pose>Unspecified</pose>
		<truncated>0</truncated>
		<difficult>0</difficult>
		<bndbox>
			<xmin>2423</xmin>
			<ymin>9</ymin>
			<xmax>3420</xmax>
			<ymax>1040</ymax>
		</bndbox>
	</object>
</annotation>
