<annotation>
	<folder>Basil</folder>
	<filename>IMG_20201113_Basil_healthy_0_4483.jpg</filename>
	<path>C:\Users\eduar\Escritorio\lalo\Basil\IMG_20201113_Basil_healthy_0_4483.jpg</path>
	<source>
		<database>Unknown</database>
	</source>
	<size>
		<width>3238</width>
		<height>2033</height>
		<depth>3</depth>
	</size>
	<segmented>0</segmented>
	<object>
		<name>Basil_healthy</name>
		<pose>Unspecified</pose>
		<truncated>0</truncated>
		<difficult>0</difficult>
		<bndbox>
			<xmin>15</xmin>
			<ymin>194</ymin>
			<xmax>2218</xmax>
			<ymax>1598</ymax>
		</bndbox>
	</object>
	<object>
		<name>Basil_healthy</name>
		<pose>Unspecified</pose>
		<truncated>0</truncated>
		<difficult>0</difficult>
		<bndbox>
			<xmin>2488</xmin>
			<ymin>408</ymin>
			<xmax>2848</xmax>
			<ymax>1008</ymax>
		</bndbox>
	</object>
	<object>
		<name>Basil_healthy</name>
		<pose>Unspecified</pose>
		<truncated>0</truncated>
		<difficult>0</difficult>
		<bndbox>
			<xmin>2569</xmin>
			<ymin>1021</ymin>
			<xmax>2922</xmax>
			<ymax>1554</ymax>
		</bndbox>
	</object>
</annotation>
