<annotation>
	<folder>Basil</folder>
	<filename>IMG_20200820_194412.jpg</filename>
	<path>C:\Users\eduar\Escritorio\lalo\Basil\IMG_20200820_194412.jpg</path>
	<source>
		<database>Unknown</database>
	</source>
	<size>
		<width>3456</width>
		<height>4608</height>
		<depth>3</depth>
	</size>
	<segmented>0</segmented>
	<object>
		<name>Radish_healthy</name>
		<pose>Unspecified</pose>
		<truncated>0</truncated>
		<difficult>0</difficult>
		<bndbox>
			<xmin>527</xmin>
			<ymin>418</ymin>
			<xmax>3412</xmax>
			<ymax>2982</ymax>
		</bndbox>
	</object>
	<object>
		<name>Radish_healthy</name>
		<pose>Unspecified</pose>
		<truncated>1</truncated>
		<difficult>0</difficult>
		<bndbox>
			<xmin>1</xmin>
			<ymin>188</ymin>
			<xmax>963</xmax>
			<ymax>1067</ymax>
		</bndbox>
	</object>
</annotation>
