<annotation>
	<folder>Basil</folder>
	<filename>IMG_20201210_Radish_healthy_0_1270.jpg</filename>
	<path>C:\Users\eduar\Escritorio\lalo\Basil\IMG_20201210_Radish_healthy_0_1270.jpg</path>
	<source>
		<database>Unknown</database>
	</source>
	<size>
		<width>3892</width>
		<height>2364</height>
		<depth>3</depth>
	</size>
	<segmented>0</segmented>
	<object>
		<name>Radish_healthy</name>
		<pose>Unspecified</pose>
		<truncated>0</truncated>
		<difficult>0</difficult>
		<bndbox>
			<xmin>277</xmin>
			<ymin>44</ymin>
			<xmax>3377</xmax>
			<ymax>1920</ymax>
		</bndbox>
	</object>
</annotation>
