<annotation>
	<folder>Basil</folder>
	<filename>IMG_20201209_Radish_healthy_0_591.jpg</filename>
	<path>C:\Users\eduar\Escritorio\lalo\Basil\IMG_20201209_Radish_healthy_0_591.jpg</path>
	<source>
		<database>Unknown</database>
	</source>
	<size>
		<width>2632</width>
		<height>3155</height>
		<depth>3</depth>
	</size>
	<segmented>0</segmented>
	<object>
		<name>Radish_healthy</name>
		<pose>Unspecified</pose>
		<truncated>0</truncated>
		<difficult>0</difficult>
		<bndbox>
			<xmin>680</xmin>
			<ymin>29</ymin>
			<xmax>2631</xmax>
			<ymax>3154</ymax>
		</bndbox>
	</object>
</annotation>
