<annotation>
	<folder>Basil</folder>
	<filename>IMG_20201209_Radish_healthy_0_769.jpg</filename>
	<path>C:\Users\eduar\Escritorio\lalo\Basil\IMG_20201209_Radish_healthy_0_769.jpg</path>
	<source>
		<database>Unknown</database>
	</source>
	<size>
		<width>3429</width>
		<height>2870</height>
		<depth>3</depth>
	</size>
	<segmented>0</segmented>
	<object>
		<name>Radish_healthy</name>
		<pose>Unspecified</pose>
		<truncated>1</truncated>
		<difficult>0</difficult>
		<bndbox>
			<xmin>40</xmin>
			<ymin>291</ymin>
			<xmax>3428</xmax>
			<ymax>2870</ymax>
		</bndbox>
	</object>
</annotation>
