<annotation>
	<folder>Basil</folder>
	<filename>IMG_20200820_194528.jpg</filename>
	<path>C:\Users\eduar\Escritorio\lalo\Basil\IMG_20200820_194528.jpg</path>
	<source>
		<database>Unknown</database>
	</source>
	<size>
		<width>3968</width>
		<height>2976</height>
		<depth>3</depth>
	</size>
	<segmented>0</segmented>
	<object>
		<name>Radish_healthy</name>
		<pose>Unspecified</pose>
		<truncated>0</truncated>
		<difficult>0</difficult>
		<bndbox>
			<xmin>1225</xmin>
			<ymin>478</ymin>
			<xmax>2816</xmax>
			<ymax>2292</ymax>
		</bndbox>
	</object>
	<object>
		<name>Radish_healthy</name>
		<pose>Unspecified</pose>
		<truncated>0</truncated>
		<difficult>0</difficult>
		<bndbox>
			<xmin>2396</xmin>
			<ymin>242</ymin>
			<xmax>3469</xmax>
			<ymax>1415</ymax>
		</bndbox>
	</object>
	<object>
		<name>Radish_healthy</name>
		<pose>Unspecified</pose>
		<truncated>0</truncated>
		<difficult>0</difficult>
		<bndbox>
			<xmin>329</xmin>
			<ymin>260</ymin>
			<xmax>1405</xmax>
			<ymax>1660</ymax>
		</bndbox>
	</object>
	<object>
		<name>Radish_healthy</name>
		<pose>Unspecified</pose>
		<truncated>1</truncated>
		<difficult>0</difficult>
		<bndbox>
			<xmin>1</xmin>
			<ymin>1265</ymin>
			<xmax>1151</xmax>
			<ymax>2914</ymax>
		</bndbox>
	</object>
	<object>
		<name>Radish_healthy</name>
		<pose>Unspecified</pose>
		<truncated>1</truncated>
		<difficult>0</difficult>
		<bndbox>
			<xmin>3334</xmin>
			<ymin>2001</ymin>
			<xmax>3968</xmax>
			<ymax>2883</ymax>
		</bndbox>
	</object>
</annotation>
