<annotation>
	<folder>Basil</folder>
	<filename>IMG_20201210_Radish_healthy_0_2832.jpg</filename>
	<path>C:\Users\eduar\Escritorio\lalo\Basil\IMG_20201210_Radish_healthy_0_2832.jpg</path>
	<source>
		<database>Unknown</database>
	</source>
	<size>
		<width>3073</width>
		<height>2383</height>
		<depth>3</depth>
	</size>
	<segmented>0</segmented>
	<object>
		<name>Radish_healthy</name>
		<pose>Unspecified</pose>
		<truncated>0</truncated>
		<difficult>0</difficult>
		<bndbox>
			<xmin>539</xmin>
			<ymin>291</ymin>
			<xmax>3058</xmax>
			<ymax>2343</ymax>
		</bndbox>
	</object>
</annotation>
