<annotation>
	<folder>Basil</folder>
	<filename>IMG_20201004_092040.jpg</filename>
	<path>C:\Users\eduar\Escritorio\lalo\Basil\IMG_20201004_092040.jpg</path>
	<source>
		<database>Unknown</database>
	</source>
	<size>
		<width>2976</width>
		<height>3968</height>
		<depth>3</depth>
	</size>
	<segmented>0</segmented>
	<object>
		<name>Cucumber_healthy</name>
		<pose>Unspecified</pose>
		<truncated>0</truncated>
		<difficult>0</difficult>
		<bndbox>
			<xmin>1081</xmin>
			<ymin>2279</ymin>
			<xmax>1944</xmax>
			<ymax>2937</ymax>
		</bndbox>
	</object>
	<object>
		<name>Cucumber_healthy</name>
		<pose>Unspecified</pose>
		<truncated>0</truncated>
		<difficult>0</difficult>
		<bndbox>
			<xmin>219</xmin>
			<ymin>1829</ymin>
			<xmax>956</xmax>
			<ymax>2548</ymax>
		</bndbox>
	</object>
	<object>
		<name>Cucumber_healthy</name>
		<pose>Unspecified</pose>
		<truncated>0</truncated>
		<difficult>0</difficult>
		<bndbox>
			<xmin>56</xmin>
			<ymin>2724</ymin>
			<xmax>738</xmax>
			<ymax>3343</ymax>
		</bndbox>
	</object>
	<object>
		<name>Cucumber_healthy</name>
		<pose>Unspecified</pose>
		<truncated>0</truncated>
		<difficult>0</difficult>
		<bndbox>
			<xmin>269</xmin>
			<ymin>3448</ymin>
			<xmax>930</xmax>
			<ymax>3879</ymax>
		</bndbox>
	</object>
	<object>
		<name>Cucumber_healthy</name>
		<pose>Unspecified</pose>
		<truncated>0</truncated>
		<difficult>0</difficult>
		<bndbox>
			<xmin>1088</xmin>
			<ymin>3517</ymin>
			<xmax>1699</xmax>
			<ymax>3942</ymax>
		</bndbox>
	</object>
	<object>
		<name>Cucumber_healthy</name>
		<pose>Unspecified</pose>
		<truncated>0</truncated>
		<difficult>0</difficult>
		<bndbox>
			<xmin>944</xmin>
			<ymin>2899</ymin>
			<xmax>1438</xmax>
			<ymax>3399</ymax>
		</bndbox>
	</object>
	<object>
		<name>Cucumber_healthy</name>
		<pose>Unspecified</pose>
		<truncated>0</truncated>
		<difficult>0</difficult>
		<bndbox>
			<xmin>1380</xmin>
			<ymin>3142</ymin>
			<xmax>1963</xmax>
			<ymax>3567</ymax>
		</bndbox>
	</object>
	<object>
		<name>Cucumber_healthy</name>
		<pose>Unspecified</pose>
		<truncated>0</truncated>
		<difficult>0</difficult>
		<bndbox>
			<xmin>1774</xmin>
			<ymin>3348</ymin>
			<xmax>2268</xmax>
			<ymax>3824</ymax>
		</bndbox>
	</object>
	<object>
		<name>Cucumber_healthy</name>
		<pose>Unspecified</pose>
		<truncated>0</truncated>
		<difficult>0</difficult>
		<bndbox>
			<xmin>1763</xmin>
			<ymin>2511</ymin>
			<xmax>2500</xmax>
			<ymax>3043</ymax>
		</bndbox>
	</object>
	<object>
		<name>Cucumber_healthy</name>
		<pose>Unspecified</pose>
		<truncated>0</truncated>
		<difficult>0</difficult>
		<bndbox>
			<xmin>1968</xmin>
			<ymin>1673</ymin>
			<xmax>2905</xmax>
			<ymax>2336</ymax>
		</bndbox>
	</object>
	<object>
		<name>Cucumber_healthy</name>
		<pose>Unspecified</pose>
		<truncated>0</truncated>
		<difficult>0</difficult>
		<bndbox>
			<xmin>1768</xmin>
			<ymin>917</ymin>
			<xmax>2594</xmax>
			<ymax>1574</ymax>
		</bndbox>
	</object>
	<object>
		<name>Cucumber_healthy</name>
		<pose>Unspecified</pose>
		<truncated>0</truncated>
		<difficult>0</difficult>
		<bndbox>
			<xmin>1038</xmin>
			<ymin>517</ymin>
			<xmax>1725</xmax>
			<ymax>886</ymax>
		</bndbox>
	</object>
	<object>
		<name>Cucumber_healthy</name>
		<pose>Unspecified</pose>
		<truncated>0</truncated>
		<difficult>0</difficult>
		<bndbox>
			<xmin>425</xmin>
			<ymin>1030</ymin>
			<xmax>1031</xmax>
			<ymax>1412</ymax>
		</bndbox>
	</object>
	<object>
		<name>Cucumber_healthy</name>
		<pose>Unspecified</pose>
		<truncated>0</truncated>
		<difficult>0</difficult>
		<bndbox>
			<xmin>943</xmin>
			<ymin>1311</ymin>
			<xmax>1856</xmax>
			<ymax>1842</ymax>
		</bndbox>
	</object>
</annotation>
