<annotation>
	<folder>Basil</folder>
	<filename>IMG_20200327_Cucumber_healthy_0_2911.jpg</filename>
	<path>C:\Users\eduar\Escritorio\lalo\Basil\IMG_20200327_Cucumber_healthy_0_2911.jpg</path>
	<source>
		<database>Unknown</database>
	</source>
	<size>
		<width>641</width>
		<height>999</height>
		<depth>3</depth>
	</size>
	<segmented>0</segmented>
	<object>
		<name>Cucumber_healthy</name>
		<pose>Unspecified</pose>
		<truncated>0</truncated>
		<difficult>0</difficult>
		<bndbox>
			<xmin>62</xmin>
			<ymin>181</ymin>
			<xmax>553</xmax>
			<ymax>589</ymax>
		</bndbox>
	</object>
</annotation>
