<annotation>
	<folder>Basil</folder>
	<filename>IMG_20201004_091954.jpg</filename>
	<path>C:\Users\eduar\Escritorio\lalo\Basil\IMG_20201004_091954.jpg</path>
	<source>
		<database>Unknown</database>
	</source>
	<size>
		<width>3456</width>
		<height>4608</height>
		<depth>3</depth>
	</size>
	<segmented>0</segmented>
	<object>
		<name>Cucumber_healthy</name>
		<pose>Unspecified</pose>
		<truncated>0</truncated>
		<difficult>0</difficult>
		<bndbox>
			<xmin>113</xmin>
			<ymin>985</ymin>
			<xmax>3083</xmax>
			<ymax>4292</ymax>
		</bndbox>
	</object>
	<object>
		<name>Cucumber_healthy</name>
		<pose>Unspecified</pose>
		<truncated>0</truncated>
		<difficult>0</difficult>
		<bndbox>
			<xmin>184</xmin>
			<ymin>49</ymin>
			<xmax>1727</xmax>
			<ymax>1228</ymax>
		</bndbox>
	</object>
	<object>
		<name>Cucumber_healthy</name>
		<pose>Unspecified</pose>
		<truncated>0</truncated>
		<difficult>0</difficult>
		<bndbox>
			<xmin>49</xmin>
			<ymin>2849</ymin>
			<xmax>791</xmax>
			<ymax>3693</ymax>
		</bndbox>
	</object>
	<object>
		<name>Cucumber_healthy</name>
		<pose>Unspecified</pose>
		<truncated>1</truncated>
		<difficult>0</difficult>
		<bndbox>
			<xmin>1</xmin>
			<ymin>3750</ymin>
			<xmax>1083</xmax>
			<ymax>4536</ymax>
		</bndbox>
	</object>
	<object>
		<name>Cucumber_healthy</name>
		<pose>Unspecified</pose>
		<truncated>0</truncated>
		<difficult>0</difficult>
		<bndbox>
			<xmin>1962</xmin>
			<ymin>336</ymin>
			<xmax>2727</xmax>
			<ymax>900</ymax>
		</bndbox>
	</object>
</annotation>
